applied_maths/__init__.py
applied_maths/pyhoc.py
applied_maths_adi10hero-0.0.2.dist-info/LICENSE
applied_maths_adi10hero-0.0.2.dist-info/METADATA
applied_maths_adi10hero-0.0.2.dist-info/WHEEL
applied_maths_adi10hero-0.0.2.dist-info/top_level.txt
applied_maths_adi10hero-0.0.2.dist-info/RECORD
