Metadata-Version: 2.1
Name: applied-maths-adi10hero
Version: 0.0.2
Summary: Calculates Higher Order Crossings of a signal
Home-page: https://github.com/ADI10HERO/pyHOC
Author: Aditya Srivastava
Author-email: adityasrivastava301199@gmail.com
License: UNKNOWN
Platform: UNKNOWN
Classifier: Programming Language :: Python :: 3
Classifier: License :: OSI Approved :: GNU General Public License v3 (GPLv3)
Classifier: Operating System :: OS Independent
Requires-Python: >=3.6
